{"updated": "2026-04-15T08:21:46.657222+00:00", "bot_running": true, "account": {"balance": 50000.0, "equity": 50000.0}, "strength": {"USD": {"score": -0.0545, "rank": 9, "slope": "down"}, "EUR": {"score": -0.027, "rank": 6, "slope": "flat"}, "GBP": {"score": -0.0464, "rank": 8, "slope": "flat"}, "JPY": {"score": 0.0304, "rank": 3, "slope": "flat"}, "AUD": {"score": 0.0828, "rank": 1, "slope": "up"}, "NZD": {"score": 0.004, "rank": 4, "slope": "flat"}, "CAD": {"score": -0.0203, "rank": 5, "slope": "flat"}, "CHF": {"score": 0.0672, "rank": 2, "slope": "up"}, "XAU": {"score": -0.0391, "rank": 7, "slope": "flat"}}, "top_pairs": [], "win_probs": {}, "regime": "trending_up", "regime_tradeable": true, "in_session": true, "session": "london", "performance": {"total": 0, "wins": 0, "losses": 0, "win_rate": 0.0, "total_pnl": 0.0}, "news": []}